MANIFEST.in
NEWS.txt
README.rst
setup.py
src/classycode/__init__.py
src/classycode/directives.py
src/classycode/formatter.py
src/classycode/tests/__init__.py
src/classycode/tests/path.py
src/classycode/tests/test_directives.py
src/classycode/tests/test_formatter.py
src/classycode/tests/test_writers.py
src/classycode/tests/util.py
src/sphinx_classy_code.egg-info/PKG-INFO
src/sphinx_classy_code.egg-info/SOURCES.txt
src/sphinx_classy_code.egg-info/dependency_links.txt
src/sphinx_classy_code.egg-info/not-zip-safe
src/sphinx_classy_code.egg-info/requires.txt
src/sphinx_classy_code.egg-info/top_level.txt