Metadata-Version: 1.1
Name: sphinx-classy-code
Version: 0.1
Summary: UNKNOWN
Home-page: https://github.com/nyergler/sphinx-classy-code
Author: Nathan Yergler
Author-email: nathan@yergler.net
License: BSD
Platform: UNKNOWN
Classifier: License :: OSI Approved :: BSD License
Classifier: Topic :: Documentation
Classifier: Topic :: Text Processing
Classifier: Programming Language :: Python :: 2
Classifier: Programming Language :: Python :: 3
